ljctoolbox/__init__.py
ljctoolbox/algorithm.py
ljctoolbox/file_parser.py
ljctoolbox/process_pool.py
ljctoolbox/thread_pool.py
ljctoolbox/timebox.py
ljctoolbox/mjson/__init__.py
ljctoolbox/mjson/hook.py
ljctoolbox/packtool/__init__.py
ljctoolbox/packtool/pack.py
ljctoolbox-0.0.1.dist-info/LICENSE
ljctoolbox-0.0.1.dist-info/METADATA
ljctoolbox-0.0.1.dist-info/WHEEL
ljctoolbox-0.0.1.dist-info/top_level.txt
ljctoolbox-0.0.1.dist-info/RECORD
