Metadata-Version: 2.1
Name: ljctoolbox
Version: 0.0.1
Summary: Ljc tool box
Home-page: UNKNOWN
Author: ljc
Author-email: liujichao.ljc@qq.com
License: GPLv3
Platform: UNKNOWN
Classifier: Development Status :: 5 - Production/Stable
Classifier: Intended Audience :: Developers
Classifier: Topic :: Software Development :: Build Tools
Classifier: License :: OSI Approved :: GNU General Public License v3 (GPLv3)
Requires-Python: <=3
